network_fallback_service/__init__.py
network_fallback_service/configure.py
network_fallback_service/main.py
network_fallback_service/network/__init__.py
network_fallback_service/network/checks.py
network_fallback_service/network/devices.py
network_fallback_service/network/routes.py
network_fallback_service/network/device_types/NetworkManager.py
network_fallback_service/network/device_types/__init__.py
network_fallback_service/network/device_types/ifupdown.py
network_fallback_service-0.1.0.dist-info/LICENSE
network_fallback_service-0.1.0.dist-info/METADATA
network_fallback_service-0.1.0.dist-info/WHEEL
network_fallback_service-0.1.0.dist-info/entry_points.txt
network_fallback_service-0.1.0.dist-info/top_level.txt
network_fallback_service-0.1.0.dist-info/RECORD
