Metadata-Version: 2.1
Name: network-fallback-service
Version: 0.1.0
Summary: Fallback to working network interfaces
Author: Nicholas Hassan
Classifier: Programming Language :: Python :: 3
Classifier: License :: OSI Approved :: GNU General Public License v3 (GPLv3)
Classifier: Operating System :: POSIX :: Linux
Requires-Python: >=3.5
License-File: LICENSE
Requires-Dist: argparse (>=1.4)
Requires-Dist: configparser (>=4.0)
Requires-Dist: apscheduler (>=3.9)
Requires-Dist: netifaces (>=0.11.0)
